pyrunjvm/__init__.py
pyrunjvm/application.py
pyrunjvm/cli.py
pyrunjvm/config/tomcat/server.xml
pyrunjvm/context.py
pyrunjvm/util.py
pyrunjvm-0.6.0.dist-info/LICENSE
pyrunjvm-0.6.0.dist-info/METADATA
pyrunjvm-0.6.0.dist-info/WHEEL
pyrunjvm-0.6.0.dist-info/entry_points.txt
pyrunjvm-0.6.0.dist-info/RECORD
