Metadata-Version: 2.1
Name: pyrunjvm
Version: 0.6.0
Summary: 
License: Apache-2.0
Author: riag
Author-email: riag@163.com
Requires-Python: >=3.8,<4.0
Classifier: License :: OSI Approved :: Apache Software License
Classifier: Programming Language :: Python :: 3
Classifier: Programming Language :: Python :: 3.8
Classifier: Programming Language :: Python :: 3.9
Classifier: Programming Language :: Python :: 3.10
Classifier: Programming Language :: Python :: 3.11
Requires-Dist: Jinja2 (>=3.1.2,<4.0.0)
Requires-Dist: click (>=7.1.2,<8.0.0)
Requires-Dist: python-dotenv (>=0.15.0,<0.16.0)
Requires-Dist: tomlkit (>=0.5.3,<0.6.0)
